pytest_testmon-2.1.4.dist-info/licenses/LICENSE
testmon/__init__.py
testmon/common.py
testmon/configure.py
testmon/db.py
testmon/process_code.py
testmon/pytest_testmon.py
testmon/testmon_core.py
pytest_testmon-2.1.4.dist-info/METADATA
pytest_testmon-2.1.4.dist-info/WHEEL
pytest_testmon-2.1.4.dist-info/entry_points.txt
pytest_testmon-2.1.4.dist-info/top_level.txt
pytest_testmon-2.1.4.dist-info/RECORD
