Metadata-Version: 2.4
Name: pytest-testmon
Version: 2.1.4
Summary: selects tests affected by changed files and methods
Author-email: Tibor Arpas <tibor@testmon.org>
License: MIT
Keywords: testing,pytest,plugin
Classifier: Development Status :: 4 - Beta
Classifier: Intended Audience :: Developers
Classifier: Operating System :: POSIX
Classifier: Operating System :: Microsoft :: Windows
Classifier: Operating System :: MacOS :: MacOS X
Classifier: Topic :: Software Development :: Testing
Classifier: Topic :: Software Development :: Libraries
Classifier: Topic :: Utilities
Classifier: Programming Language :: Python
Classifier: Framework :: Pytest
Requires-Python: >=3.8
License-File: LICENSE
Requires-Dist: pytest<9,>=5
Requires-Dist: coverage<8,>=6
Dynamic: license-file
